gcpds/visualizations/__init__.py
gcpds/visualizations/accuracy/__init__.py
gcpds/visualizations/accuracy/agco.py
gcpds/visualizations/connectivities/__init__.py
gcpds/visualizations/connectivities/circos.py
gcpds/visualizations/series/__init__.py
gcpds/visualizations/series/eeg.py
gcpds/visualizations/topoplots/__init__.py
gcpds_visualizations-0.4.dist-info/LICENSE
gcpds_visualizations-0.4.dist-info/METADATA
gcpds_visualizations-0.4.dist-info/WHEEL
gcpds_visualizations-0.4.dist-info/top_level.txt
gcpds_visualizations-0.4.dist-info/RECORD
